Workbook
Name acumulado_periodo: INVESTIMENTOS!$E$16
Name aporte: INVESTIMENTOS!$E$13
Name aporte_real: 'FÉRIAS - COMPRAS'!$E$9
Name aporte1: 'FÉRIAS - COMPRAS'!$E$12
Name aporte2: 'FÉRIAS - COMPRAS'!$D$20
Name dividendos: INVESTIMENTOS!$E$17
Name meses_carro: 'FÉRIAS - COMPRAS'!$D$24
Name meses_carro2: 'FÉRIAS - COMPRAS'!$E$24
Name meses_ferias: 'FÉRIAS - COMPRAS'!$E$14
Name objetivo_Ferias: 'FÉRIAS - COMPRAS'!$E$13
Name objetivo2: 'FÉRIAS - COMPRAS'!$D$21
Name patrimonio_carro1: 'FÉRIAS - COMPRAS'!$D$26
Name patrimonio_carro2: 'FÉRIAS - COMPRAS'!$E$26
Name patrimonio_ferias: 'FÉRIAS - COMPRAS'!$E$16
Name perfil: INVESTIMENTOS!$E$7
Name qtd_anos: INVESTIMENTOS!$E$14
Name rendimento_carteira: INVESTIMENTOS!$E$9
Name salario: INVESTIMENTOS!$E$8
Name sugestao_invest: INVESTIMENTOS!$E$10
Name taxa_rendimento: INVESTIMENTOS!$E$15
Name veiculo: 'FÉRIAS - COMPRAS'!$D$22
Name veiculo_depreciado: 'FÉRIAS - COMPRAS'!$E$22

Sheet INVESTIMENTOS
F5: {=_xlfn.IFS(perfil="Conservador","Este perfil prioriza segurança e liquidez",perfil="Moderado","Este perfil busca equilíbrio entre segurança e rentabilidade",perfil="Agressivo","Este perfil foca totalmente na Rentabilidade")} -> Este perfil prioriza segurança e liquidez
C6: CONFIGURAÇÕES
C7: Perfil de Investidor | E7: Conservador
C8: Salário | E8: 8540
C9: Rendimento da Carteira | E9: 0.0085
C10: Sugestão de Investimento (30%) | E10: =salario*30% -> 2562
C12: INVESTIMENTO MENSAL
C13: Quanto investir por mês? | E13: 2000
C14: Por quantos anos? | E14: 5
C15: Taxa de rendimento mensal? | E15: 0.01079
C16: Patrimônio vai acumulado? | E16: =FV(taxa_rendimento,qtd_anos*12,aporte*-1) -> 167553.83
C17: Dividendos por mês.? | E17: =acumulado_periodo*rendimento_carteira -> 1424.2075
C19: CENÁRIOS | D19: Patrimônio | E19: Dividendos
B20: 2 | C20: Quantos em 2 anos | D20: =FV(taxa_rendimento,B20*12,aporte*-1) -> 54455.255 | E20: =D20*rendimento_carteira -> 462.86966
B21: 5 | C21: Quantos em 5 anos | D21: =FV(taxa_rendimento,B21*12,aporte*-1) -> 167553.83 | E21: =D21*rendimento_carteira -> 1424.2075
B22: 10 | C22: Quantos em 10 anos | D22: =FV(taxa_rendimento,B22*12,aporte*-1) -> 486568.43 | E22: =D22*rendimento_carteira -> 4135.8316
B23: 20 | C23: Quantos em 20 anos | D23: =FV(taxa_rendimento,B23*12,aporte*-1) -> 2250396.8 | E23: =D23*rendimento_carteira -> 19128.373
B24: 30 | C24: Quantos em 30 anos | D24: =FV(taxa_rendimento,B24*12,aporte*-1) -> 8644339.3 | E24: =D24*rendimento_carteira -> 73476.884
C26: CENÁRIOS CASO INVISTA O VALOR SUGERIDO | D26: PATRIMÔNIO | E26: DIVIDENDOS
C27: Quantos em 2 anos | D27: =FV(taxa_rendimento,B20*12,sugestao_invest*-1) -> 69757.181 | E27: =D27*rendimento_carteira -> 592.93604
C28: Quantos em 5 anos | D28: =FV(taxa_rendimento,B21*12,sugestao_invest*-1) -> 214636.45 | E28: =D28*rendimento_carteira -> 1824.4099
C29: Quantos em 10 anos | D29: =FV(taxa_rendimento,B22*12,sugestao_invest*-1) -> 623294.15 | E29: =D29*rendimento_carteira -> 5298.0003
C30: Quantos em 20 anos | D30: =FV(taxa_rendimento,B23*12,sugestao_invest*-1) -> 2882758.3 | E30: =D30*rendimento_carteira -> 24503.446
C31: Quantos em 30 anos | D31: =FV(taxa_rendimento,B24*12,sugestao_invest*-1) -> 11073399 | E31: =D31*rendimento_carteira -> 94123.889
C33: INVESTIMENTOS EM FUNDOS IMOBILIÁRIOS
C34: VALOR A SER INVESTIDO | D34: =aporte -> 2000
C36: TIPOS DE FIIS | D36: PERCENTUAL | E36: VALORES
C37: PAPEL | D37: =VLOOKUP(perfil&"-"&C37,'TABELA APOIO'!A:D,4,0) -> 0.3 | E37: =$D$34*D37 -> 600
C38: TIJOLO | D38: =VLOOKUP(perfil&"-"&C38,'TABELA APOIO'!A:D,4,0) -> 0.4 | E38: =$D$34*D38 -> 800
C39: HIBRIDO | D39: =VLOOKUP(perfil&"-"&C39,'TABELA APOIO'!A:D,4,0) -> 0.2 | E39: =$D$34*D39 -> 400
C40: FOFs | D40: =VLOOKUP(perfil&"-"&C40,'TABELA APOIO'!A:D,4,0) -> 0.05 | E40: =$D$34*D40 -> 100
C41: DESENVOLVIMENTO | D41: =VLOOKUP(perfil&"-"&C41,'TABELA APOIO'!A:D,4,0) -> 0.05 | E41: =$D$34*D41 -> 100
C42: HOTELARIA | D42: =VLOOKUP(perfil&"-"&C42,'TABELA APOIO'!A:D,4,0) -> 0 | E42: =$D$34*D42 -> 0
E43: =SUM(E37:E42) -> 2000
C44: ="Investidor"&" - "&perfil -> Investidor - Conservador
F53: =HYPERLINK("#perfil","Voltar do Topo") -> Voltar do Topo

Sheet FÉRIAS - COMPRAS
C6: CONFIGURAÇÕES
C7: SALÁRIO | E7: 8650
C8: SUGESTÃO DE GASTOS | E8: =E7*30% -> 2595
C9: VALOR REAL DE APORTE | E9: 2000
C11: FÉRIAS PROGRAMADAS
C12: VALOR DE APORTE | E12: 600
C13: OBJETIVO | E13: 9000
C14: TOTAL DE MESES | E14: =ROUNDDOWN(NPER(E15,-aporte1,0,objetivo_Ferias),) -> 14
C15: TAXA DE RENDIMENTO MENSAL | E15: 0.0103
C16: PATRIMÔNIO ACUMULADO | E16: =FV(E15,meses_ferias,aporte1*-1) -> 8986.2201
C19: COMPRA DE CARRO NOVO | D19: ATÉ 14 MESES | E19: ="DE 15°"&" AO "&" "&(D24+E24)&" " &"MÊS" -> DE 15° AO 49 MÊS
C20: VALOR DE APORTE | D20: =E9-E12 -> 1400 | E20: =E9 -> 2000
C21: OBJETIVO | D21: 165000 | E21: 172000
C22: VENDA CARRO EM USO | D22: 75000 | E22: 68000
C23: OBJETIVO REAL | D23: =objetivo2-veiculo -> 90000 | E23: =E21-veiculo_depreciado-patrimonio_carro1 -> 83032.153
C24: TOTAL DE MESES | D24: =meses_ferias -> 14 | E24: =ROUND(NPER(E25,-E20,0,E23),0) -> 35
C25: TAXA DE RENDIMENTO MENSAL | D25: 0.0103 | E25: 0.0103
C26: PATRIMÔNIO ACUMULADO | D26: =FV(D25,D24,D20*-1) -> 20967.847 | E26: =FV(E25,E24,E20*-1) -> 83767.849
C27: SOMA DOS PATRIMÔNIOS ACUMULADOS | E27: =E26+D26 -> 104735.7
C29: * Os valores do objetivo (compra do Carro) foi considerado um aumento no bem novo e uma depreciação no bem usado
C30: ** Entendendo Objetivo Real da coluna "E" : Objetivo (valor do Bem) diminui o valor do carro em uso nemos o patrimônio
C31: acumulado nos primeiros 14 meses tendo um valor menor ao objetivo real da coluna D devido a esse saldo

Sheet TABELA APOIO
B1: PERFIL DE INVESTIDOR | C1: TIPOS DE FIIS | D1: %
A2: =B2&"-"&C2 -> Conservador-PAPEL | B2: Conservador | C2: PAPEL | D2: 0.3
A3: =B3&"-"&C3 -> Conservador-TIJOLO | B3: Conservador | C3: TIJOLO | D3: 0.4
A4: =B4&"-"&C4 -> Conservador-HIBRIDO | B4: Conservador | C4: HIBRIDO | D4: 0.2
A5: =B5&"-"&C5 -> Conservador-FOFs | B5: Conservador | C5: FOFs | D5: 0.05
A6: =B6&"-"&C6 -> Conservador-DESENVOLVIMENTO | B6: Conservador | C6: DESENVOLVIMENTO | D6: 0.05
A7: =B7&"-"&C7 -> Conservador-HOTELARIA | B7: Conservador | C7: HOTELARIA | D7: 0
A8: =B8&"-"&C8 -> Moderado-PAPEL | B8: Moderado | C8: PAPEL | D8: 0.3
A9: =B9&"-"&C9 -> Moderado-TIJOLO | B9: Moderado | C9: TIJOLO | D9: 0.35
A10: =B10&"-"&C10 -> Moderado-HIBRIDO | B10: Moderado | C10: HIBRIDO | D10: 0.1
A11: =B11&"-"&C11 -> Moderado-FOFs | B11: Moderado | C11: FOFs | D11: 0.1
A12: =B12&"-"&C12 -> Moderado-DESENVOLVIMENTO | B12: Moderado | C12: DESENVOLVIMENTO | D12: 0.05
A13: =B13&"-"&C13 -> Moderado-HOTELARIA | B13: Moderado | C13: HOTELARIA | D13: 0.1
... A19: =B19&"-"&C19 -> Agressivo-HOTELARIA | B19: Agressivo | C19: HOTELARIA | D19: 0.05
F21: 0.0105
F22: 600
F23: 9000
F25: =ROUNDDOWN(NPER(F21,-F22,0,F23),0) -> 14 | H25: =50-F25 -> 36
F27: =NPER(1.05%,600,0,9000) -> -16.4076
I28: =F22*F25 -> 8400
F29: -16.4076
